{
  "data": {
    "projects": [
      {
        "id": "rec0LSDh7zpYkAeom",
        "name": "HOPR",
        "introduction": "HOPR is a privacy-preserving, decentralized messaging protocol that empowers users to communicate securely and anonymously. By utilizing a mixnet approach, HOPR ensures data privacy and resists metadata analysis. The HOPR token enables users to participate in the network, earn rewards, and govern the protocol, ensuring a sustainable and community-driven ecosystem.",
        "website": "https://hoprnet.org/",
        "twitter": "https://twitter.com/hoprnet",
        "marketCap": 20740296,
        "tokenSymbol": "HOPR",
        "explorerUrl": "https://etherscan.io/token/0xf5581dfefd8fb0e4aec526be659cfab1f8c781da",
        "mediumUrl": "https://medium.com/hoprnet",
        "redditUrl": "https://www.reddit.com/r/Hopr/",
        "githubUrl": "https://github.com/hoprnet",
        "whitepaperUrl": "https://hoprnet.org/docs/whitepaper.pdf",
        "tags": [
          {
            "id": "recgqAdiHbbhN3qwr",
            "name": "Decentralized VPN"
          }
        ],
        "chains": []
      },
      {
        "id": "rec0QOfGctiduqNTX",
        "name": "Sui Names",
        "introduction": "A decentralized digital identity focused on the Sui ecosystem.",
        "website": "https://sui-names.com/",
        "twitter": null,
        "marketCap": null,
        "tokenSymbol": null,
        "explorerUrl": null,
        "mediumUrl": null,
        "redditUrl": null,
        "githubUrl": null,
        "whitepaperUrl": null,
        "tags": [
          {
            "id": "recruNGUb5CjfScHw",
            "name": "Infrastructure"
          }
        ],
        "chains": [
          {
            "id": "recsjTJv52vVYdOqg",
            "name": "Sui"
          }
        ]
      },
      {
        "id": "rec1Gz7L1VzcXPS6X",
        "name": "Sui Gallery",
        "introduction": "An NFT market built on Sui.",
        "website": "https://www.sui.gallery/",
        "twitter": null,
        "marketCap": null,
        "tokenSymbol": null,
        "explorerUrl": null,
        "mediumUrl": null,
        "redditUrl": null,
        "githubUrl": null,
        "whitepaperUrl": null,
        "tags": [
          {
            "id": "recAaP55eAVmXWO7x",
            "name": "NFT Markets"
          }
        ],
        "chains": [
          {
            "id": "recsjTJv52vVYdOqg",
            "name": "Sui"
          }
        ]
      },
      {
        "id": "rec5dUoAkukJ6mRVH",
        "name": "Mysterium",
        "introduction": "Mysterium is a decentralized, open-source VPN platform that leverages blockchain technology to provide a secure and anonymous internet experience. By creating a peer-to-peer network of VPN service providers, Mysterium ensures data privacy and security for users. The native token, MYST, is used to access services, reward providers, and govern the platform.",
        "website": "https://mysterium.network/",
        "twitter": "https://twitter.com/MysteriumNet",
        "marketCap": 5415460,
        "tokenSymbol": "MYST",
        "explorerUrl": "https://etherscan.io/token/0x4bfred2b3f90804b6b23d1ee10ccf5d5be654b2e",
        "mediumUrl": "https://medium.com/mysterium-network",
        "redditUrl": "https://www.reddit.com/r/MysteriumNetwork/",
        "githubUrl": "https://github.com/MysteriumNetwork",
        "whitepaperUrl": "https://mysterium.network/whitepaper/",
        "tags": [
          {
            "id": "recgqAdiHbbhN3qwr",
            "name": "Decentralized VPN"
          }
        ],
        "chains": []
      },
      {
        "id": "rec60SdBb81dajFAc",
        "name": "Morphis Wallet",
        "introduction": "Morphis wallet is a friendly wallet to get started with your web3 journey. Morphis allows you to manage all your web3 assets in one place, from tokens and NFTs to game assets and your gateway to thousands of dApps. Morphis will be your single access point to the unlimited potential of the web3 world.",
        "website": "https://morphiswallet.com/",
        "twitter": "https://twitter.com/morphis_network",
        "marketCap": null,
        "tokenSymbol": null,
        "explorerUrl": null,
        "mediumUrl": null,
        "redditUrl": null,
        "githubUrl": null,
        "whitepaperUrl": null,
        "tags": [
          {
            "id": "recjlK9nrNPVACbL0",
            "name": "Wallet"
          }
        ],
        "chains": [
          {
            "id": "recsjTJv52vVYdOqg",
            "name": "Sui"
          }
        ]
      },
      {
        "id": "rec6Tw1wWJdKdtTOM",
        "name": "Dragon SUI",
        "introduction": "An NFT market built on Sui and enables minting, collecting and trading NFTs.",
        "website": "https://dragonsui.com/",
        "twitter": null,
        "marketCap": null,
        "tokenSymbol": null,
        "explorerUrl": null,
        "mediumUrl": null,
        "redditUrl": null,
        "githubUrl": null,
        "whitepaperUrl": null,
        "tags": [
          {
            "id": "recAaP55eAVmXWO7x",
            "name": "NFT Markets"
          }
        ],
        "chains": [
          {
            "id": "recsjTJv52vVYdOqg",
            "name": "Sui"
          }
        ]
      },
      {
        "id": "rec6x0kE3DkkbkmL2",
        "name": "Glass Wallet",
        "introduction": "Glass Wallet is a non-custodial cryptocurrency wallet that provides users with a secure and easy-to-use platform to manage their digital assets. It supports various cryptocurrencies, including Bitcoin, Ethereum, and Litecoin, and allows users to store, send, receive, and exchange their digital assets. Glass Wallet is available for mobile devices.",
        "website": "https://glasswallet.app/",
        "twitter": "https://twitter.com/GlassWalletapp",
        "marketCap": null,
        "tokenSymbol": null,
        "explorerUrl": null,
        "mediumUrl": null,
        "redditUrl": null,
        "githubUrl": null,
        "whitepaperUrl": null,
        "tags": [
          {
            "id": "recjlK9nrNPVACbL0",
            "name": "Wallet"
          }
        ],
        "chains": [
          {
            "id": "recsjTJv52vVYdOqg",
            "name": "Sui"
          }
        ]
      },
      {
        "id": "rec6xWh742hWDcNs8",
        "name": "Tidalswap",
        "introduction": "An advanced cross-chain AMM protocol built on Aptos and Sui.",
        "website": "https://tidalswap.com/",
        "twitter": null,
        "marketCap": null,
        "tokenSymbol": null,
        "explorerUrl": null,
        "mediumUrl": null,
        "redditUrl": null,
        "githubUrl": null,
        "whitepaperUrl": null,
        "tags": [
          {
            "id": "recjij7AtXPBhoL3j",
            "name": "Dex"
          }
        ],
        "chains": [
          {
            "id": "recsjTJv52vVYdOqg",
            "name": "Sui"
          }
        ]
      },
      {
        "id": "rec7XygwzN5Yrommk",
        "name": "Suia.io",
        "introduction": "The first POAP application built on Sui and it has been launched on Devnet.",
        "website": "https://suia.io/",
        "twitter": null,
        "marketCap": null,
        "tokenSymbol": null,
        "explorerUrl": null,
        "mediumUrl": null,
        "redditUrl": null,
        "githubUrl": null,
        "whitepaperUrl": null,
        "tags": [
          {
            "id": "reccOPMXhhegGDuTP",
            "name": "NFT Collection"
          }
        ],
        "chains": [
          {
            "id": "recsjTJv52vVYdOqg",
            "name": "Sui"
          }
        ]
      },
      {
        "id": "rec8UxgEE74XQ08aK",
        "name": "Fewcha Wallet",
        "introduction": "Fewcha Wallet is a non-custodial cryptocurrency wallet that offers users a simple and secure platform to manage their digital assets. It supports various cryptocurrencies, including Bitcoin, Ethereum, and Litecoin, and allows users to store, send, receive, and exchange their digital assets. Fewcha Wallet is available for mobile devices.",
        "website": null,
        "twitter": null,
        "marketCap": null,
        "tokenSymbol": null,
        "explorerUrl": null,
        "mediumUrl": null,
        "redditUrl": null,
        "githubUrl": null,
        "whitepaperUrl": null,
        "tags": [
          {
            "id": "recjlK9nrNPVACbL0",
            "name": "Wallet"
          }
        ],
        "chains": [
          {
            "id": "recsjTJv52vVYdOqg",
            "name": "Sui"
          }
        ]
      },
      {
        "id": "rec9dxvKbwnTVJPvW",
        "name": "Deeper Network",
        "introduction": "Deeper Network is an innovative blockchain project that aims to provide a secure, private, and fair internet experience for users worldwide. Combining hardware and software solutions, it offers a decentralized VPN service, ensuring online privacy and security. The native token, DPR, is used to incentivize users and power the ecosystem's various services and functionalities.",
        "website": "https://www.deeper.network/",
        "twitter": "https://twitter.com/deeper_network",
        "marketCap": 13630206,
        "tokenSymbol": "DPR",
        "explorerUrl": "https://etherscan.io/token/0xf3ae5d769e153ef72b4e3591ac004e89f48107a1",
        "mediumUrl": "https://deeper-network.medium.com/",
        "redditUrl": "https://www.reddit.com/r/DeeperNetwork/",
        "githubUrl": "https://github.com/deeper-chain/deeper-chain",
        "whitepaperUrl": "https://deeper.network/whitepaper_en.pdf",
        "tags": [
          {
            "id": "recgqAdiHbbhN3qwr",
            "name": "Decentralized VPN"
          }
        ],
        "chains": []
      },
      {
        "id": "recBjI0mvWH7uHb2x",
        "name": "StarSpace",
        "introduction": "An NFT market built on Sui waiting to be launched.",
        "website": "https://www.starspace.io/",
        "twitter": null,
        "marketCap": null,
        "tokenSymbol": null,
        "explorerUrl": null,
        "mediumUrl": null,
        "redditUrl": null,
        "githubUrl": null,
        "whitepaperUrl": null,
        "tags": [
          {
            "id": "recAaP55eAVmXWO7x",
            "name": "NFT Markets"
          }
        ],
        "chains": [
          {
            "id": "recsjTJv52vVYdOqg",
            "name": "Sui"
          }
        ]
      },
      {
        "id": "recCxYdDNR74Hlnrh",
        "name": "Kx.Finance",
        "introduction": "A DeFi/DEX aggregator built on Sui and enables the trading of bonds, leverage and NFTs.",
        "website": "https://www.kx.finance/",
        "twitter": null,
        "marketCap": null,
        "tokenSymbol": null,
        "explorerUrl": null,
        "mediumUrl": null,
        "redditUrl": null,
        "githubUrl": null,
        "whitepaperUrl": null,
        "tags": [
          {
            "id": "recjij7AtXPBhoL3j",
            "name": "Dex"
          }
        ],
        "chains": [
          {
            "id": "recsjTJv52vVYdOqg",
            "name": "Sui"
          }
        ]
      },
      {
        "id": "recEEymBiCypNEXQn",
        "name": "TokenMaskaLabs",
        "introduction": "An NFT collection built on Sui.",
        "website": "https://twitter.com/TokenMasksLabs",
        "twitter": null,
        "marketCap": null,
        "tokenSymbol": null,
        "explorerUrl": null,
        "mediumUrl": null,
        "redditUrl": null,
        "githubUrl": null,
        "whitepaperUrl": null,
        "tags": [
          {
            "id": "reccOPMXhhegGDuTP",
            "name": "NFT Collection"
          }
        ],
        "chains": [
          {
            "id": "recsjTJv52vVYdOqg",
            "name": "Sui"
          }
        ]
      },
      {
        "id": "recI8coXXhUS8Q068",
        "name": "Araya Finance",
        "introduction": "A one-stop DeFi protocol built on Sui.",
        "website": "https://www.arayafi.org/",
        "twitter": null,
        "marketCap": null,
        "tokenSymbol": null,
        "explorerUrl": null,
        "mediumUrl": null,
        "redditUrl": null,
        "githubUrl": null,
        "whitepaperUrl": null,
        "tags": [
          {
            "id": "rec9txQaAdTdKG8aS",
            "name": "Defi"
          }
        ],
        "chains": [
          {
            "id": "recsjTJv52vVYdOqg",
            "name": "Sui"
          }
        ]
      },
      {
        "id": "recIlfOGDRB9cZi5e",
        "name": "Sui Punks",
        "introduction": "The first NFT collectible in the Sui NFT ecosystem and is a pixelated NFT project.",
        "website": "https://suipunks.xyz/",
        "twitter": null,
        "marketCap": null,
        "tokenSymbol": null,
        "explorerUrl": null,
        "mediumUrl": null,
        "redditUrl": null,
        "githubUrl": null,
        "whitepaperUrl": null,
        "tags": [
          {
            "id": "reccOPMXhhegGDuTP",
            "name": "NFT Collection"
          }
        ],
        "chains": [
          {
            "id": "recsjTJv52vVYdOqg",
            "name": "Sui"
          }
        ]
      },
      {
        "id": "recK8G7lnDpLlAm1t",
        "name": "Sui Name Service",
        "introduction": "A decentralized digital identity service in the Sui ecosystem and is currently in beta.",
        "website": "https://www.suins.io",
        "twitter": null,
        "marketCap": null,
        "tokenSymbol": null,
        "explorerUrl": null,
        "mediumUrl": null,
        "redditUrl": null,
        "githubUrl": null,
        "whitepaperUrl": null,
        "tags": [
          {
            "id": "recruNGUb5CjfScHw",
            "name": "Infrastructure"
          }
        ],
        "chains": [
          {
            "id": "recsjTJv52vVYdOqg",
            "name": "Sui"
          }
        ]
      },
      {
        "id": "recLtQc2DDPEQfqkg",
        "name": "Coin98",
        "introduction": "Coin98 Wallet is a secure and user-friendly non-custodial cryptocurrency wallet that supports multiple blockchains, including Ethereum, Binance Smart Chain, and Solana.",
        "website": null,
        "twitter": null,
        "marketCap": null,
        "tokenSymbol": null,
        "explorerUrl": null,
        "mediumUrl": null,
        "redditUrl": null,
        "githubUrl": null,
        "whitepaperUrl": null,
        "tags": [
          {
            "id": "recjlK9nrNPVACbL0",
            "name": "Wallet"
          }
        ],
        "chains": [
          {
            "id": "recsjTJv52vVYdOqg",
            "name": "Sui"
          }
        ]
      },
      {
        "id": "recNDGg7hLzcgVC6r",
        "name": "PLASMAVERSE",
        "introduction": "A metaverse ARPG game running on Aptos/Sui blockchains.",
        "website": "https://www.plasmaverse.xyz/",
        "twitter": null,
        "marketCap": null,
        "tokenSymbol": null,
        "explorerUrl": null,
        "mediumUrl": null,
        "redditUrl": null,
        "githubUrl": null,
        "whitepaperUrl": null,
        "tags": [
          {
            "id": "recurwxmBmR0NX6iU",
            "name": "GameFi"
          }
        ],
        "chains": [
          {
            "id": "recsjTJv52vVYdOqg",
            "name": "Sui"
          }
        ]
      },
      {
        "id": "recOhaMivwgLqW78L",
        "name": "Lucky Kat",
        "introduction": "An award-winning mobile game studio with games that have been downloaded more than 200 million times on App Store and its first sold-out NFT project “Panzerdogs” is a top 10 Solana game.",
        "website": "https://careers.lucky-kat.com/",
        "twitter": null,
        "marketCap": null,
        "tokenSymbol": null,
        "explorerUrl": null,
        "mediumUrl": null,
        "redditUrl": null,
        "githubUrl": null,
        "whitepaperUrl": null,
        "tags": [
          {
            "id": "recurwxmBmR0NX6iU",
            "name": "GameFi"
          }
        ],
        "chains": [
          {
            "id": "recsjTJv52vVYdOqg",
            "name": "Sui"
          }
        ]
      },
      {
        "id": "recPccCbOquuRd7Qd",
        "name": "SuiSwap",
        "introduction": "A DEX built on Uniswap V2 and has gone live.",
        "website": "https://suiswap.app/",
        "twitter": null,
        "marketCap": null,
        "tokenSymbol": null,
        "explorerUrl": null,
        "mediumUrl": null,
        "redditUrl": null,
        "githubUrl": null,
        "whitepaperUrl": null,
        "tags": [
          {
            "id": "recjij7AtXPBhoL3j",
            "name": "Dex"
          }
        ],
        "chains": [
          {
            "id": "recsjTJv52vVYdOqg",
            "name": "Sui"
          }
        ]
      },
      {
        "id": "recPqdr9bnYwJ4rjY",
        "name": "Substratum",
        "introduction": "Substratum is a decentralized, open-source platform that aims to create a censorship-resistant and secure internet by leveraging a global network of nodes. The platform allows users to host and access web content securely and anonymously, bypassing restrictions and surveillance. The native token, SUB, powers the ecosystem by incentivizing node operators and enabling access to services.",
        "website": "https://substratum.net/",
        "twitter": "https://twitter.com/SubstratumNet",
        "marketCap": 140400,
        "tokenSymbol": "SUB",
        "explorerUrl": "https://etherscan.io/token/0x12480e24eb5bec1a9d4369cab6a80cad3c0a377a",
        "mediumUrl": "https://medium.com/@substratumnet",
        "redditUrl": "https://www.reddit.com/r/SubstratumNetwork/",
        "githubUrl": "https://github.com/SubstratumNetwork",
        "whitepaperUrl": "https://substratum.net/wp-content/uploads/2017/08/SubstratumWhitepaper.pdf",
        "tags": [
          {
            "id": "recgqAdiHbbhN3qwr",
            "name": "Decentralized VPN"
          }
        ],
        "chains": []
      },
      {
        "id": "recREiahJH0dPKIa2",
        "name": "Palladium",
        "introduction": "An AMM cross-chain DEX and is yet to be launched.",
        "website": "https://twitter.com/Palladium_DEX",
        "twitter": null,
        "marketCap": null,
        "tokenSymbol": null,
        "explorerUrl": null,
        "mediumUrl": null,
        "redditUrl": null,
        "githubUrl": null,
        "whitepaperUrl": null,
        "tags": [
          {
            "id": "recjij7AtXPBhoL3j",
            "name": "Dex"
          }
        ],
        "chains": [
          {
            "id": "recsjTJv52vVYdOqg",
            "name": "Sui"
          }
        ]
      },
      {
        "id": "recU1VuO5ybmV4nj2",
        "name": "Wave Wallet",
        "introduction": "Waves is a wallet built with a security-first principles for the Sui blockchain. An enclave for your digital assets.",
        "website": null,
        "twitter": null,
        "marketCap": null,
        "tokenSymbol": null,
        "explorerUrl": null,
        "mediumUrl": null,
        "redditUrl": null,
        "githubUrl": null,
        "whitepaperUrl": null,
        "tags": [
          {
            "id": "recjlK9nrNPVACbL0",
            "name": "Wallet"
          }
        ],
        "chains": [
          {
            "id": "recsjTJv52vVYdOqg",
            "name": "Sui"
          }
        ]
      },
      {
        "id": "recV53gGZzB1YwICB",
        "name": "Tachyon Protocol",
        "introduction": "Tachyon Protocol is a decentralized, privacy-focused internet protocol designed to improve online security, privacy, and access to restricted content. Built on the V SYSTEMS blockchain, Tachyon Protocol leverages advanced encryption and routing techniques to create a fast and secure VPN-like experience. The native token, IPX, is used for accessing services and governing the ecosystem.",
        "website": "https://tachyon.eco/",
        "twitter": "https://twitter.com/tachyon_eco",
        "marketCap": 230583,
        "tokenSymbol": "IPX",
        "explorerUrl": "https://explorer.v.systems/token/TWZZfKFqcaNVe5TrphLRNEm5DQFnBRJMjDDByqv84",
        "mediumUrl": "https://tachyon.eco/",
        "redditUrl": "https://www.reddit.com/r/TachyonIPX/",
        "githubUrl": "https://github.com/tachyon-protocol",
        "whitepaperUrl": "https://tachyon.eco/TachyonWhitePaper.pdf",
        "tags": [
          {
            "id": "recgqAdiHbbhN3qwr",
            "name": "Decentralized VPN"
          }
        ],
        "chains": []
      },
      {
        "id": "recWLzyqhq4lXXkz6",
        "name": "Quask",
        "introduction": "Provides peer-to-peer expert consultation in various fields around the world, aiming to create a Web3 professional think tank based on social networks and to pay for knowledge.",
        "website": "https://www.quask.xyz/",
        "twitter": null,
        "marketCap": null,
        "tokenSymbol": null,
        "explorerUrl": null,
        "mediumUrl": null,
        "redditUrl": null,
        "githubUrl": null,
        "whitepaperUrl": null,
        "tags": [
          {
            "id": "recruNGUb5CjfScHw",
            "name": "Infrastructure"
          }
        ],
        "chains": [
          {
            "id": "recsjTJv52vVYdOqg",
            "name": "Sui"
          }
        ]
      },
      {
        "id": "recX6D1adcT1rSXm8",
        "name": "Shinami",
        "introduction": "Aims to provide the driving force for the next wave of DApps and to facilitate the construction of Sui blockchain for developers without necessarily running and maintaining nodes.",
        "website": "https://www.shinami.com/",
        "twitter": null,
        "marketCap": null,
        "tokenSymbol": null,
        "explorerUrl": null,
        "mediumUrl": null,
        "redditUrl": null,
        "githubUrl": null,
        "whitepaperUrl": null,
        "tags": [
          {
            "id": "recruNGUb5CjfScHw",
            "name": "Infrastructure"
          }
        ],
        "chains": [
          {
            "id": "recsjTJv52vVYdOqg",
            "name": "Sui"
          }
        ]
      },
      {
        "id": "recXlb0MfQjsLIv20",
        "name": "OmniBTC",
        "introduction": "A decentralized omnichain financial platform built by the ChainX team based on the LayerZero protocol. OmniBTC proposed a new pathway for OmniLending.",
        "website": "https://app.omnibtc.finance/swap",
        "twitter": null,
        "marketCap": null,
        "tokenSymbol": null,
        "explorerUrl": null,
        "mediumUrl": null,
        "redditUrl": null,
        "githubUrl": null,
        "whitepaperUrl": null,
        "tags": [
          {
            "id": "rec9txQaAdTdKG8aS",
            "name": "Defi"
          }
        ],
        "chains": [
          {
            "id": "recsjTJv52vVYdOqg",
            "name": "Sui"
          }
        ]
      },
      {
        "id": "recZsMQSiIGYzwDxH",
        "name": "BlueMove",
        "introduction": "The first-ever NFT market for communities built on Aptos and Sui that proactively rewards investors, collectors and artists.",
        "website": "https://sui.bluemove.net/",
        "twitter": null,
        "marketCap": null,
        "tokenSymbol": null,
        "explorerUrl": null,
        "mediumUrl": null,
        "redditUrl": null,
        "githubUrl": null,
        "whitepaperUrl": null,
        "tags": [
          {
            "id": "recAaP55eAVmXWO7x",
            "name": "NFT Markets"
          }
        ],
        "chains": [
          {
            "id": "recsjTJv52vVYdOqg",
            "name": "Sui"
          }
        ]
      },
      {
        "id": "rechKAzZ2YksHEG1n",
        "name": "SuiPad",
        "introduction": "The first-ever Launchpad built on Sui and it includes functions like IDO, ISO and INO, etc.",
        "website": "https://suipad.xyz/",
        "twitter": null,
        "marketCap": null,
        "tokenSymbol": null,
        "explorerUrl": null,
        "mediumUrl": null,
        "redditUrl": null,
        "githubUrl": null,
        "whitepaperUrl": null,
        "tags": [
          {
            "id": "rec9txQaAdTdKG8aS",
            "name": "Defi"
          }
        ],
        "chains": [
          {
            "id": "recsjTJv52vVYdOqg",
            "name": "Sui"
          }
        ]
      },
      {
        "id": "rechaIdhMnrQ8RQTx",
        "name": "Kriya DEX",
        "introduction": "A derivative DEX built on Sui and allows a leverage multiplier of up to 20.",
        "website": "https://efficacy.finance/kriya-sui-dex/",
        "twitter": null,
        "marketCap": null,
        "tokenSymbol": null,
        "explorerUrl": null,
        "mediumUrl": null,
        "redditUrl": null,
        "githubUrl": null,
        "whitepaperUrl": null,
        "tags": [
          {
            "id": "recjij7AtXPBhoL3j",
            "name": "Dex"
          }
        ],
        "chains": [
          {
            "id": "recsjTJv52vVYdOqg",
            "name": "Sui"
          }
        ]
      },
      {
        "id": "rechifdfsaLh5XIaD",
        "name": "Ethos",
        "introduction": "Ethos Wallet is a non-custodial cryptocurrency wallet that provides users with a simple and secure platform to manage their digital assets. It allows users to store, send, receive, and exchange various cryptocurrencies, including Bitcoin, Ethereum, and Litecoin. Ethos Wallet is available for mobile devices and desktop computers.",
        "website": null,
        "twitter": null,
        "marketCap": null,
        "tokenSymbol": null,
        "explorerUrl": null,
        "mediumUrl": null,
        "redditUrl": null,
        "githubUrl": null,
        "whitepaperUrl": null,
        "tags": [
          {
            "id": "recjlK9nrNPVACbL0",
            "name": "Wallet"
          }
        ],
        "chains": [
          {
            "id": "recsjTJv52vVYdOqg",
            "name": "Sui"
          }
        ]
      },
      {
        "id": "reciegatatzwCjNPU",
        "name": "Abel Finance",
        "introduction": "A cross-chain asset lending platform that also supports using LP Token and NFT as collateral to lend stablecoins.",
        "website": "https://abelfinance.xyz/#/markets",
        "twitter": null,
        "marketCap": null,
        "tokenSymbol": null,
        "explorerUrl": null,
        "mediumUrl": null,
        "redditUrl": null,
        "githubUrl": null,
        "whitepaperUrl": null,
        "tags": [
          {
            "id": "rec9txQaAdTdKG8aS",
            "name": "Defi"
          }
        ],
        "chains": [
          {
            "id": "recsjTJv52vVYdOqg",
            "name": "Sui"
          }
        ]
      },
      {
        "id": "recjcmKV0kWVS7iGs",
        "name": "SuiBirds",
        "introduction": "The first MEME NFT bird built on Sui.",
        "website": "https://twitter.com/SuiBirds",
        "twitter": null,
        "marketCap": null,
        "tokenSymbol": null,
        "explorerUrl": null,
        "mediumUrl": null,
        "redditUrl": null,
        "githubUrl": null,
        "whitepaperUrl": null,
        "tags": [
          {
            "id": "reccOPMXhhegGDuTP",
            "name": "NFT Collection"
          }
        ],
        "chains": [
          {
            "id": "recsjTJv52vVYdOqg",
            "name": "Sui"
          }
        ]
      },
      {
        "id": "reckcbPjMecU5MCqP",
        "name": "F1 Dog",
        "introduction": "The first NFT dog racing game built on Sui and Aptos blockchains.",
        "website": "https://f1.dog/",
        "twitter": null,
        "marketCap": null,
        "tokenSymbol": null,
        "explorerUrl": null,
        "mediumUrl": null,
        "redditUrl": null,
        "githubUrl": null,
        "whitepaperUrl": null,
        "tags": [
          {
            "id": "recurwxmBmR0NX6iU",
            "name": "GameFi"
          }
        ],
        "chains": [
          {
            "id": "recsjTJv52vVYdOqg",
            "name": "Sui"
          }
        ]
      },
      {
        "id": "reclMZ6Hvt0mb5Jzf",
        "name": "Sentinel",
        "introduction": "Sentinel is a decentralized VPN platform designed to offer users a secure, anonymous, and censorship-resistant internet experience. Built on the Cosmos Network, Sentinel allows users to access a global network of VPN service providers, ensuring data privacy and security. The native token, DVPN, enables users to access services, reward providers, and govern the platform.",
        "website": "https://sentinel.co/",
        "twitter": "https://twitter.com/Sentinel_co",
        "marketCap": 7691040,
        "tokenSymbol": "SENT",
        "explorerUrl": "https://etherscan.io/token/0xa44e5137293e855b1b7bc7e2c6f8cd796ffcb037",
        "mediumUrl": "https://medium.com/sentinel",
        "redditUrl": "https://www.reddit.com/r/Sentinel_co/",
        "githubUrl": "https://github.com/Sentinel-official",
        "whitepaperUrl": "https://github.com/sentinel-official/sentinel/blob/master/README.md",
        "tags": [
          {
            "id": "recgqAdiHbbhN3qwr",
            "name": "Decentralized VPN"
          }
        ],
        "chains": []
      },
      {
        "id": "recp7n7ILqN1vKs2O",
        "name": "Orchid",
        "introduction": "Orchid is a decentralized, open-source platform that offers a privacy-oriented, peer-to-peer marketplace for bandwidth sharing. It enables users to access the internet securely and anonymously by connecting to a global network of VPN providers. Orchid's native token, OXT, powers the platform and incentivizes participants to contribute to the network's growth and sustainability.",
        "website": "https://www.orchid.com/",
        "twitter": "https://twitter.com/orchidprotocol",
        "marketCap": 86704283,
        "tokenSymbol": "OXT",
        "explorerUrl": "https://etherscan.io/token/0x4575f41308EC1483f3d399aa9a2826d74Da13Deb",
        "mediumUrl": "https://medium.com/orchid",
        "redditUrl": "https://www.reddit.com/r/orchid/",
        "githubUrl": "https://github.com/OrchidTechnologies",
        "whitepaperUrl": "https://orchid.com/whitepaper",
        "tags": [
          {
            "id": "recgqAdiHbbhN3qwr",
            "name": "Decentralized VPN"
          }
        ],
        "chains": []
      },
      {
        "id": "recrFU1MaYBa6md2I",
        "name": "KeepSake",
        "introduction": "An NFT market built on Sui and has gone live for interaction.",
        "website": "https://keepsake.gg/",
        "twitter": null,
        "marketCap": null,
        "tokenSymbol": null,
        "explorerUrl": null,
        "mediumUrl": null,
        "redditUrl": null,
        "githubUrl": null,
        "whitepaperUrl": null,
        "tags": [
          {
            "id": "recAaP55eAVmXWO7x",
            "name": "NFT Markets"
          }
        ],
        "chains": [
          {
            "id": "recsjTJv52vVYdOqg",
            "name": "Sui"
          }
        ]
      },
      {
        "id": "recu5kuhDT3iQZNvo",
        "name": "Axelar Network",
        "introduction": "A Web3 cross-chain application that aims to provide a smooth cross-chain experience for public chains and their ecosystems.",
        "website": "https://axelar.network/",
        "twitter": null,
        "marketCap": null,
        "tokenSymbol": null,
        "explorerUrl": null,
        "mediumUrl": null,
        "redditUrl": null,
        "githubUrl": null,
        "whitepaperUrl": null,
        "tags": [
          {
            "id": "recHw8cINcIMu9B07",
            "name": "Cross-chain Bridge"
          }
        ],
        "chains": [
          {
            "id": "recsjTJv52vVYdOqg",
            "name": "Sui"
          }
        ]
      },
      {
        "id": "reculZIaLHC0qiCdV",
        "name": "Wormhole",
        "introduction": "A cross-chain protocol backed by Solana. In October 2022, Solana released an Ethereum token cross-chain bridge.",
        "website": "https://wormhole.com/",
        "twitter": null,
        "marketCap": null,
        "tokenSymbol": null,
        "explorerUrl": null,
        "mediumUrl": null,
        "redditUrl": null,
        "githubUrl": null,
        "whitepaperUrl": null,
        "tags": [
          {
            "id": "recHw8cINcIMu9B07",
            "name": "Cross-chain Bridge"
          }
        ],
        "chains": [
          {
            "id": "recsjTJv52vVYdOqg",
            "name": "Sui"
          }
        ]
      },
      {
        "id": "recx8CcFQmOes5i4j",
        "name": "MovEX",
        "introduction": "The first AMM+ order book DEX with hybrid liquidity on Sui, which combines the advantages of AMM and order book to provide everyone with a smooth trading experience by creating a hybrid liquidity pool.",
        "website": "https://www.movex.exchange/",
        "twitter": null,
        "marketCap": null,
        "tokenSymbol": null,
        "explorerUrl": null,
        "mediumUrl": null,
        "redditUrl": null,
        "githubUrl": null,
        "whitepaperUrl": null,
        "tags": [
          {
            "id": "recjij7AtXPBhoL3j",
            "name": "Dex"
          }
        ],
        "chains": [
          {
            "id": "recsjTJv52vVYdOqg",
            "name": "Sui"
          }
        ]
      },
      {
        "id": "recyayLOsvuuy3YsQ",
        "name": "Suiet",
        "introduction": "the Sui wallet made for everyone",
        "website": null,
        "twitter": null,
        "marketCap": null,
        "tokenSymbol": null,
        "explorerUrl": null,
        "mediumUrl": null,
        "redditUrl": null,
        "githubUrl": null,
        "whitepaperUrl": null,
        "tags": [
          {
            "id": "recjlK9nrNPVACbL0",
            "name": "Wallet"
          }
        ],
        "chains": [
          {
            "id": "recsjTJv52vVYdOqg",
            "name": "Sui"
          }
        ]
      }
    ]
  }
}
